qformatpy-1.0.2.dist-info/METADATA
qformatpy-1.0.2.dist-info/WHEEL
qformatpy-1.0.2.dist-info/entry_points.txt
qformatpy-1.0.2.dist-info/licenses/LICENSE
qformatpy/__init__.py
qformatpy/_qformatpy.py
qformatpy/constants.py
qformatpy-1.0.2.dist-info/RECORD
