Metadata-Version: 2.1
Name: qformatpy
Version: 1.0.2
Summary: Simple to use fixed-point library.
Keywords: DSP,Fixed-point,Signal-Processing,Qformat
Author-Email: Eric Macedo <ericsmacedo@gmail.com>
Classifier: Programming Language :: Python :: 3
Classifier: Programming Language :: Python :: 3.10
Classifier: Programming Language :: Python :: 3.11
Classifier: Programming Language :: Python :: 3.12
Classifier: Programming Language :: Python :: 3.13
Classifier: Operating System :: OS Independent
Project-URL: Documentation, https://qformatpy.readthedocs.io/en/latest/
Project-URL: Source Code, https://github.com/ericsmacedo/qformatpy
Requires-Python: <4.0,>=3.10.0
Requires-Dist: numba>=0.61.2
Requires-Dist: numpy
